_winsock.cp311-win_amd64.pyd
uwinsock/__init__.py
uwinsock/fakesocket.py
gladie.uwinsock-0.1.0.dist-info/METADATA
gladie.uwinsock-0.1.0.dist-info/WHEEL
gladie.uwinsock-0.1.0.dist-info/top_level.txt
gladie.uwinsock-0.1.0.dist-info/RECORD
